md_dihedrals/__init__.py
md_dihedrals/__pkginfo__.py
md_dihedrals/dihedrals_analysis/__init__.py
md_dihedrals/dihedrals_analysis/histogram.py
md_dihedrals/gui/__init__.py
md_dihedrals/gui/main_window.py
md_dihedrals/readers/__init__.py
md_dihedrals/readers/dihedrals_file.py
md_dihedrals/readers/xvg_reader.py
md_dihedrals-0.0.5.data/scripts/md_dihedrals
md_dihedrals-0.0.5.dist-info/LICENSE
md_dihedrals-0.0.5.dist-info/METADATA
md_dihedrals-0.0.5.dist-info/WHEEL
md_dihedrals-0.0.5.dist-info/top_level.txt
md_dihedrals-0.0.5.dist-info/RECORD
